dtscalibration/__init__.py
dtscalibration/calibrate_utils.py
dtscalibration/dts_accessor.py
dtscalibration/dts_accessor_utils.py
dtscalibration/plot.py
dtscalibration/variance_helpers.py
dtscalibration/variance_stokes.py
dtscalibration/calibration/section_utils.py
dtscalibration/io/__init__.py
dtscalibration/io/apsensing.py
dtscalibration/io/sensornet.py
dtscalibration/io/sensortran.py
dtscalibration/io/silixa.py
dtscalibration/io/utils.py
dtscalibration-3.1.0.dist-info/METADATA
dtscalibration-3.1.0.dist-info/WHEEL
dtscalibration-3.1.0.dist-info/licenses/AUTHORS.rst
dtscalibration-3.1.0.dist-info/licenses/LICENSE
dtscalibration-3.1.0.dist-info/RECORD
