Metadata-Version: 2.3
Name: dtscalibration
Version: 3.1.0
Summary: Load Distributed Temperature Sensing (DTS) files, calibrate the temperature and estimate its uncertainty.
Author: Bas des Tombe, Bart Schilperoort
Maintainer: Bas des Tombe, Bart Schilperoort
License-Expression: BSD-3-Clause
License-File: AUTHORS.rst
License-File: LICENSE
Keywords: DTS,calibration,confidence intervals,distributed temperature sensing
Classifier: Development Status :: 5 - Production/Stable
Classifier: Intended Audience :: Developers
Classifier: Intended Audience :: Science/Research
Classifier: License :: OSI Approved :: BSD License
Classifier: Operating System :: Microsoft :: Windows
Classifier: Operating System :: POSIX
Classifier: Operating System :: Unix
Classifier: Programming Language :: Python
Classifier: Programming Language :: Python :: 3.9
Classifier: Programming Language :: Python :: 3.10
Classifier: Programming Language :: Python :: 3.11
Classifier: Programming Language :: Python :: 3.12
Classifier: Topic :: Utilities
Requires-Python: <3.13,>=3.9
Requires-Dist: dask[distributed]
Requires-Dist: matplotlib
Requires-Dist: nc-time-axis>=1.4.1
Requires-Dist: netcdf4>=1.6.4
Requires-Dist: numpy
Requires-Dist: pandas
Requires-Dist: pyyaml>=6.0.1
Requires-Dist: scipy
Requires-Dist: xarray[accel]
Requires-Dist: xmltodict
Provides-Extra: dev
Requires-Dist: black[jupyter]; extra == 'dev'
Requires-Dist: bump2version; extra == 'dev'
Requires-Dist: hatch; extra == 'dev'
Requires-Dist: jupyter; extra == 'dev'
Requires-Dist: mypy; extra == 'dev'
Requires-Dist: nbformat; extra == 'dev'
Requires-Dist: pandas-stubs; extra == 'dev'
Requires-Dist: pytest; extra == 'dev'
Requires-Dist: pytest-cov; extra == 'dev'
Requires-Dist: pytest-xdist; extra == 'dev'
Requires-Dist: ruff; extra == 'dev'
Requires-Dist: types-pyyaml; extra == 'dev'
Requires-Dist: types-xmltodict; extra == 'dev'
Provides-Extra: docs
Requires-Dist: coverage[toml]; extra == 'docs'
Requires-Dist: ipykernel; extra == 'docs'
Requires-Dist: ipython; extra == 'docs'
Requires-Dist: jupyter-client; extra == 'docs'
Requires-Dist: matplotlib>=3.0.0; extra == 'docs'
Requires-Dist: myst-parser; extra == 'docs'
Requires-Dist: nbsphinx; extra == 'docs'
Requires-Dist: pypandoc; extra == 'docs'
Requires-Dist: recommonmark; extra == 'docs'
Requires-Dist: sphinx; extra == 'docs'
Requires-Dist: sphinx-autoapi; extra == 'docs'
Requires-Dist: sphinx-automodapi; extra == 'docs'
Requires-Dist: sphinx-autosummary-accessors; extra == 'docs'
Requires-Dist: sphinx-rtd-theme; extra == 'docs'
